README.md
setup.py
OpenAP/__init__.py
OpenAP/correction.py
OpenAP/frequency.py
OpenAP/helper.py
OpenAP/histogram.py
OpenAP/image.py
OpenAP/logging.py
OpenAP/psf.py
OpenAP/star.py
astropenap.egg-info/PKG-INFO
astropenap.egg-info/SOURCES.txt
astropenap.egg-info/dependency_links.txt
astropenap.egg-info/not-zip-safe
astropenap.egg-info/top_level.txt