Metadata-Version: 1.0
Name: astropenap
Version: 0.2
Summary: easy image processor
Home-page: https://github.com/jinleic/OpenAP
Author: Xinlun Cheng
Author-email: UNKNOWN
License: MIT
Platform: UNKNOWN
